<annotation>
	<folder>Batch 3</folder>
	<filename>Image4 143.jpg</filename>
	<path>D:\My Files\Downloads\Batch 3\Image4 143.jpg</path>
	<source>
		<database>Unknown</database>
	</source>
	<size>
		<width>512</width>
		<height>256</height>
		<depth>1</depth>
	</size>
	<segmented>0</segmented>
	<object>
		<name>u1loss</name>
		<pose>Unspecified</pose>
		<truncated>0</truncated>
		<difficult>0</difficult>
		<bndbox>
			<xmin>358</xmin>
			<ymin>97</ymin>
			<xmax>379</xmax>
			<ymax>139</ymax>
		</bndbox>
	</object>
	<object>
		<name>u2healthy</name>
		<pose>Unspecified</pose>
		<truncated>0</truncated>
		<difficult>0</difficult>
		<bndbox>
			<xmin>330</xmin>
			<ymin>84</ymin>
			<xmax>361</xmax>
			<ymax>134</ymax>
		</bndbox>
	</object>
	<object>
		<name>u3healthy</name>
		<pose>Unspecified</pose>
		<truncated>0</truncated>
		<difficult>0</difficult>
		<bndbox>
			<xmin>304</xmin>
			<ymin>78</ymin>
			<xmax>340</xmax>
			<ymax>133</ymax>
		</bndbox>
	</object>
	<object>
		<name>u4healthy</name>
		<pose>Unspecified</pose>
		<truncated>0</truncated>
		<difficult>0</difficult>
		<bndbox>
			<xmin>289</xmin>
			<ymin>76</ymin>
			<xmax>312</xmax>
			<ymax>129</ymax>
		</bndbox>
	</object>
	<object>
		<name>u5chipped</name>
		<pose>Unspecified</pose>
		<truncated>0</truncated>
		<difficult>0</difficult>
		<bndbox>
			<xmin>274</xmin>
			<ymin>83</ymin>
			<xmax>293</xmax>
			<ymax>130</ymax>
		</bndbox>
	</object>
	<object>
		<name>u6decay</name>
		<pose>Unspecified</pose>
		<truncated>0</truncated>
		<difficult>0</difficult>
		<bndbox>
			<xmin>263</xmin>
			<ymin>82</ymin>
			<xmax>282</xmax>
			<ymax>130</ymax>
		</bndbox>
	</object>
	<object>
		<name>u7decay</name>
		<pose>Unspecified</pose>
		<truncated>0</truncated>
		<difficult>0</difficult>
		<bndbox>
			<xmin>256</xmin>
			<ymin>83</ymin>
			<xmax>268</xmax>
			<ymax>129</ymax>
		</bndbox>
	</object>
	<object>
		<name>u8healthy</name>
		<pose>Unspecified</pose>
		<truncated>0</truncated>
		<difficult>0</difficult>
		<bndbox>
			<xmin>249</xmin>
			<ymin>81</ymin>
			<xmax>262</xmax>
			<ymax>130</ymax>
		</bndbox>
	</object>
	<object>
		<name>u9decay</name>
		<pose>Unspecified</pose>
		<truncated>0</truncated>
		<difficult>0</difficult>
		<bndbox>
			<xmin>240</xmin>
			<ymin>79</ymin>
			<xmax>253</xmax>
			<ymax>129</ymax>
		</bndbox>
	</object>
	<object>
		<name>u10decay</name>
		<pose>Unspecified</pose>
		<truncated>0</truncated>
		<difficult>0</difficult>
		<bndbox>
			<xmin>231</xmin>
			<ymin>79</ymin>
			<xmax>244</xmax>
			<ymax>128</ymax>
		</bndbox>
	</object>
	<object>
		<name>u11decay</name>
		<pose>Unspecified</pose>
		<truncated>0</truncated>
		<difficult>0</difficult>
		<bndbox>
			<xmin>221</xmin>
			<ymin>75</ymin>
			<xmax>234</xmax>
			<ymax>129</ymax>
		</bndbox>
	</object>
	<object>
		<name>u12healthy</name>
		<pose>Unspecified</pose>
		<truncated>0</truncated>
		<difficult>0</difficult>
		<bndbox>
			<xmin>206</xmin>
			<ymin>73</ymin>
			<xmax>225</xmax>
			<ymax>128</ymax>
		</bndbox>
	</object>
	<object>
		<name>u13healthy</name>
		<pose>Unspecified</pose>
		<truncated>0</truncated>
		<difficult>0</difficult>
		<bndbox>
			<xmin>192</xmin>
			<ymin>77</ymin>
			<xmax>207</xmax>
			<ymax>129</ymax>
		</bndbox>
	</object>
	<object>
		<name>u14healthy</name>
		<pose>Unspecified</pose>
		<truncated>0</truncated>
		<difficult>0</difficult>
		<bndbox>
			<xmin>167</xmin>
			<ymin>81</ymin>
			<xmax>195</xmax>
			<ymax>129</ymax>
		</bndbox>
	</object>
	<object>
		<name>u15healthy</name>
		<pose>Unspecified</pose>
		<truncated>0</truncated>
		<difficult>0</difficult>
		<bndbox>
			<xmin>151</xmin>
			<ymin>93</ymin>
			<xmax>179</xmax>
			<ymax>132</ymax>
		</bndbox>
	</object>
	<object>
		<name>i1healthy</name>
		<pose>Unspecified</pose>
		<truncated>0</truncated>
		<difficult>0</difficult>
		<bndbox>
			<xmin>345</xmin>
			<ymin>167</ymin>
			<xmax>387</xmax>
			<ymax>194</ymax>
		</bndbox>
	</object>
	<object>
		<name>i2healthy</name>
		<pose>Unspecified</pose>
		<truncated>0</truncated>
		<difficult>0</difficult>
		<bndbox>
			<xmin>334</xmin>
			<ymin>141</ymin>
			<xmax>372</xmax>
			<ymax>188</ymax>
		</bndbox>
	</object>
	<object>
		<name>i3healthy</name>
		<pose>Unspecified</pose>
		<truncated>0</truncated>
		<difficult>0</difficult>
		<bndbox>
			<xmin>318</xmin>
			<ymin>135</ymin>
			<xmax>348</xmax>
			<ymax>178</ymax>
		</bndbox>
	</object>
	<object>
		<name>i4healthy</name>
		<pose>Unspecified</pose>
		<truncated>0</truncated>
		<difficult>0</difficult>
		<bndbox>
			<xmin>303</xmin>
			<ymin>135</ymin>
			<xmax>325</xmax>
			<ymax>180</ymax>
		</bndbox>
	</object>
	<object>
		<name>i5healthy</name>
		<pose>Unspecified</pose>
		<truncated>0</truncated>
		<difficult>0</difficult>
		<bndbox>
			<xmin>289</xmin>
			<ymin>129</ymin>
			<xmax>309</xmax>
			<ymax>181</ymax>
		</bndbox>
	</object>
	<object>
		<name>i6chipped</name>
		<pose>Unspecified</pose>
		<truncated>0</truncated>
		<difficult>0</difficult>
		<bndbox>
			<xmin>278</xmin>
			<ymin>129</ymin>
			<xmax>295</xmax>
			<ymax>181</ymax>
		</bndbox>
	</object>
	<object>
		<name>i7healthy</name>
		<pose>Unspecified</pose>
		<truncated>0</truncated>
		<difficult>0</difficult>
		<bndbox>
			<xmin>265</xmin>
			<ymin>132</ymin>
			<xmax>283</xmax>
			<ymax>180</ymax>
		</bndbox>
	</object>
	<object>
		<name>i8healthy</name>
		<pose>Unspecified</pose>
		<truncated>0</truncated>
		<difficult>0</difficult>
		<bndbox>
			<xmin>249</xmin>
			<ymin>130</ymin>
			<xmax>271</xmax>
			<ymax>173</ymax>
		</bndbox>
	</object>
	<object>
		<name>i9decay</name>
		<pose>Unspecified</pose>
		<truncated>0</truncated>
		<difficult>0</difficult>
		<bndbox>
			<xmin>239</xmin>
			<ymin>130</ymin>
			<xmax>258</xmax>
			<ymax>176</ymax>
		</bndbox>
	</object>
	<object>
		<name>i10decay</name>
		<pose>Unspecified</pose>
		<truncated>0</truncated>
		<difficult>0</difficult>
		<bndbox>
			<xmin>225</xmin>
			<ymin>132</ymin>
			<xmax>244</xmax>
			<ymax>178</ymax>
		</bndbox>
	</object>
	<object>
		<name>i11healthy</name>
		<pose>Unspecified</pose>
		<truncated>0</truncated>
		<difficult>0</difficult>
		<bndbox>
			<xmin>214</xmin>
			<ymin>129</ymin>
			<xmax>231</xmax>
			<ymax>177</ymax>
		</bndbox>
	</object>
	<object>
		<name>i12healthy</name>
		<pose>Unspecified</pose>
		<truncated>0</truncated>
		<difficult>0</difficult>
		<bndbox>
			<xmin>203</xmin>
			<ymin>126</ymin>
			<xmax>218</xmax>
			<ymax>179</ymax>
		</bndbox>
	</object>
	<object>
		<name>i13healthy</name>
		<pose>Unspecified</pose>
		<truncated>0</truncated>
		<difficult>0</difficult>
		<bndbox>
			<xmin>188</xmin>
			<ymin>130</ymin>
			<xmax>203</xmax>
			<ymax>178</ymax>
		</bndbox>
	</object>
	<object>
		<name>i14healthy</name>
		<pose>Unspecified</pose>
		<truncated>0</truncated>
		<difficult>0</difficult>
		<bndbox>
			<xmin>166</xmin>
			<ymin>133</ymin>
			<xmax>195</xmax>
			<ymax>174</ymax>
		</bndbox>
	</object>
	<object>
		<name>i15healthy</name>
		<pose>Unspecified</pose>
		<truncated>0</truncated>
		<difficult>0</difficult>
		<bndbox>
			<xmin>151</xmin>
			<ymin>139</ymin>
			<xmax>179</xmax>
			<ymax>177</ymax>
		</bndbox>
	</object>
</annotation>
